{
  "client secret file path": "client_secret.json",
  "push methods": {
    "discord": {
      "webhook url": "",
      "content": "<@&discord_role_id> Live now! {}\nStarted at: {started_at}\nGame: {game_name}"
    },
    "telegram": {
      "token": "",
      "chat id": [],
      "content": "Test Push {link}\nStarted at: {started_at}\nGame: {game_name}"
    },
    "twitter": {
      "api key": "",
      "api secret key": "",
      "bearer token": "Unused for now",
      "access token": "",
      "access token secret": "",
      "content": "Bot Twitter push test\n\n{link}\nStarted at: {started_at}\nGame: {game_name}"
    },
    "reddit": {
      "reddit api": "",
      "content": "add_some_mention_thingy_here {}"
    }
  }
}
